<databaseChangeLog xmlns="http://www.liquibase.org/xml/ns/dbchangelog" xmlns:xsi="http://www.w3.org/2001/XMLSchema-instance" xsi:schemaLocation="http://www.liquibase.org/xml/ns/dbchangelog http://www.liquibase.org/xml/ns/dbchangelog/dbchangelog-3.4.xsd">
    <changeSet id="create-table-item_type" author="Saphyra">
        <preConditions onFail="MARK_RAN">
            <not>
                <tableExists schemaName="elite_base" tableName="item_type"/>
            </not>
        </preConditions>

        <createTable  schemaName="elite_base" tableName="item_type">
            <column name="item_name" type="varchar(255)" >
                <constraints nullable="false"/>
            </column>
            <column name="type" type="varchar(255)"/>
        </createTable>

        <addPrimaryKey schemaName="elite_base" tableName="item_type" columnNames="item_name" constraintName="item_type-pk"/>
    </changeSet>
</databaseChangeLog>